{"doi": "10.1097/fpc.0000000000000249", "doi_url": "https://doi.org/10.1097/fpc.0000000000000249", "title": "Prediction of early weight gain during psychotropic treatment using a combinatorial model with clinical and genetic markers", "genre": "journal-article", "is_paratext": false, "published_date": "2016-12-01", "year": 2016, "journal_name": "Pharmacogenetics and Genomics", "journal_issns": "1744-6872", "journal_issn_l": "1744-6872", "journal_is_oa": false, "journal_is_in_doaj": false, "publisher": "Ovid Technologies (Wolters Kluwer Health)", "is_oa": true, "oa_status": "green", "has_repository_copy": true, "best_oa_location": {"updated": "2022-03-23T05:58:16.790347", "url": "https://serval.unil.ch/resource/serval:BIB_BFD29890FF60.P001/REF.pdf", "url_for_pdf": "https://serval.unil.ch/resource/serval:BIB_BFD29890FF60.P001/REF.pdf", "url_for_landing_page": "https://serval.unil.ch/resource/serval:BIB_BFD29890FF60.P001/REF.pdf", "evidence": "oa repository (via OAI-PMH doi match)", "license": null, "version": "acceptedVersion", "host_type": "repository", "is_best": true, "pmh_id": "oai:serval.unil.ch:BIB_BFD29890FF60", "endpoint_id": "90389dd407c73f9e281", "repository_institution": "Universit\u00e9 de Lausanne - SERVAL", "oa_date": "2020-11-07"}, "first_oa_location": {"updated": "2022-03-23T05:58:16.790347", "url": "https://serval.unil.ch/resource/serval:BIB_BFD29890FF60.P001/REF.pdf", "url_for_pdf": "https://serval.unil.ch/resource/serval:BIB_BFD29890FF60.P001/REF.pdf", "url_for_landing_page": "https://serval.unil.ch/resource/serval:BIB_BFD29890FF60.P001/REF.pdf", "evidence": "oa repository (via OAI-PMH doi match)", "license": null, "version": "acceptedVersion", "host_type": "repository", "is_best": true, "pmh_id": "oai:serval.unil.ch:BIB_BFD29890FF60", "endpoint_id": "90389dd407c73f9e281", "repository_institution": "Universit\u00e9 de Lausanne - SERVAL", "oa_date": "2020-11-07"}, "oa_locations": [{"updated": "2022-03-23T05:58:16.790347", "url": "https://serval.unil.ch/resource/serval:BIB_BFD29890FF60.P001/REF.pdf", "url_for_pdf": "https://serval.unil.ch/resource/serval:BIB_BFD29890FF60.P001/REF.pdf", "url_for_landing_page": "https://serval.unil.ch/resource/serval:BIB_BFD29890FF60.P001/REF.pdf", "evidence": "oa repository (via OAI-PMH doi match)", "license": null, "version": "acceptedVersion", "host_type": "repository", "is_best": true, "pmh_id": "oai:serval.unil.ch:BIB_BFD29890FF60", "endpoint_id": "90389dd407c73f9e281", "repository_institution": "Universit\u00e9 de Lausanne - SERVAL", "oa_date": "2020-11-07"}], "oa_locations_embargoed": [], "updated": "2022-03-02T04:23:52.448549", "data_standard": 2, "z_authors": [{"given": "Frederik", "family": "Vandenberghe", "sequence": "first"}, {"given": "N\u00faria", "family": "Saig\u00ed-Morgui", "sequence": "additional"}, {"given": "Aur\u00e9lie", "family": "Delacr\u00e9taz", "sequence": "additional"}, {"given": "Lina", "family": "Quteineh", "sequence": "additional"}, {"given": "S\u00e9verine", "family": "Crettol", "sequence": "additional"}, {"given": "Nicolas", "family": "Ansermot", "sequence": "additional"}, {"given": "Mehdi", "family": "Gholam-Rezaee", "sequence": "additional"}, {"given": "Armin", "family": "von Gunten", "sequence": "additional"}, {"given": "Philippe", "family": "Conus", "sequence": "additional"}, {"given": "Chin B.", "family": "Eap", "sequence": "additional"}]}