{"doi": "10.1111/j.1365-2591.2008.01471.x", "doi_url": "https://doi.org/10.1111/j.1365-2591.2008.01471.x", "title": "Cytotoxicity of endodontic materials over 6-weeksex vivo", "genre": "journal-article", "is_paratext": false, "published_date": "2008-12-01", "year": 2008, "journal_name": "International Endodontic Journal", "journal_issns": "0143-2885,1365-2591", "journal_issn_l": "0143-2885", "journal_is_oa": false, "journal_is_in_doaj": false, "publisher": "Wiley", "is_oa": false, "oa_status": "closed", "has_repository_copy": false, "best_oa_location": null, "first_oa_location": null, "oa_locations": [], "oa_locations_embargoed": [], "updated": "2021-01-18T13:02:57.948422", "data_standard": 2, "z_authors": [{"given": "M. G.", "family": "Brackett", "sequence": "first"}, {"given": "A.", "family": "Marshall", "sequence": "additional"}, {"given": "P. E.", "family": "Lockwood", "sequence": "additional"}, {"given": "J. B.", "family": "Lewis", "sequence": "additional"}, {"given": "R. L. W.", "family": "Messer", "sequence": "additional"}, {"given": "S.", "family": "Bouillaguet", "sequence": "additional"}, {"given": "J. C.", "family": "Wataha", "sequence": "additional"}]}