{"doi": "10.1007/s00330-019-06319-0", "doi_url": "https://doi.org/10.1007/s00330-019-06319-0", "title": "Compressed sensing MRI of different organs: ready for clinical daily practice?", "genre": "journal-article", "is_paratext": false, "published_date": "2019-07-01", "year": 2019, "journal_name": "European Radiology", "journal_issns": "0938-7994,1432-1084", "journal_issn_l": "0938-7994", "journal_is_oa": false, "journal_is_in_doaj": false, "publisher": "Springer Science and Business Media LLC", "is_oa": false, "oa_status": "closed", "has_repository_copy": false, "best_oa_location": null, "first_oa_location": null, "oa_locations": [], "oa_locations_embargoed": [], "updated": "2021-01-14T23:01:43.626060", "data_standard": 2, "z_authors": [{"ORCID": "http://orcid.org/0000-0002-1487-3588", "given": "B\u00e9n\u00e9dicte Marie Anne", "family": "Delattre", "sequence": "first", "authenticated-orcid": false}, {"given": "Sana", "family": "Boudabbous", "sequence": "additional"}, {"given": "Catrina", "family": "Hansen", "sequence": "additional"}, {"given": "Angeliki", "family": "Neroladaki", "sequence": "additional"}, {"given": "Anne-Lise", "family": "Hachulla", "sequence": "additional"}, {"given": "Maria Isabel", "family": "Vargas", "sequence": "additional"}]}