{"doi": "10.1089/acm.2020.0216", "doi_url": "https://doi.org/10.1089/acm.2020.0216", "title": "Mindfulness Training for Adults with Attention-Deficit/Hyperactivity Disorder: Implementation of Mindful Awareness Practices in a French-Speaking Attention-Deficit/Hyperactivity Disorder Unit", "genre": "journal-article", "is_paratext": false, "published_date": "2021-02-01", "year": 2021, "journal_name": "The Journal of Alternative and Complementary Medicine", "journal_issns": "1075-5535,1557-7708", "journal_issn_l": "1075-5535", "journal_is_oa": false, "journal_is_in_doaj": false, "publisher": "Mary Ann Liebert Inc", "is_oa": false, "oa_status": "closed", "has_repository_copy": false, "best_oa_location": null, "first_oa_location": null, "oa_locations": [], "oa_locations_embargoed": [], "updated": "2022-04-18T00:16:48.299401", "data_standard": 2, "z_authors": [{"given": "Rosetta", "family": "Nicastro", "sequence": "first", "affiliation": [{"name": "Department of Psychiatry, Service of Psychiatric Specialties, Geneva University Hospitals, Geneva, Switzerland."}, {"name": "Department of Psychiatry, University of Geneva, Geneva, Switzerland."}]}, {"given": "Fran\u00e7oise", "family": "Jermann", "sequence": "additional", "affiliation": [{"name": "Department of Psychiatry, Service of Psychiatric Specialties, Geneva University Hospitals, Geneva, Switzerland."}]}, {"given": "Sophie", "family": "Bluteau Blin", "sequence": "additional", "affiliation": [{"name": "Department of Psychiatry, Service of Psychiatric Specialties, Geneva University Hospitals, Geneva, Switzerland."}]}, {"given": "Caroline", "family": "Waeber", "sequence": "additional", "affiliation": [{"name": "Department of Psychiatry, Service of Psychiatric Specialties, Geneva University Hospitals, Geneva, Switzerland."}]}, {"given": "Nader", "family": "Perroud", "sequence": "additional", "affiliation": [{"name": "Department of Psychiatry, Service of Psychiatric Specialties, Geneva University Hospitals, Geneva, Switzerland."}, {"name": "Department of Psychiatry, University of Geneva, Geneva, Switzerland."}, {"name": "Department of Psychiatry, Faculty of Medicine, University of Geneva, Geneva, Switzerland."}, {"name": "Department of Psychiatry, Dalhousie University, Halifax, Nova Scotia, Canada."}]}]}