{"doi": "10.1016/j.prosdent.2019.07.013", "doi_url": "https://doi.org/10.1016/j.prosdent.2019.07.013", "title": "Use of an attachment system with angulated abutments and polyetheretherketone inserts to retain a maxillary overdenture: A clinical report", "genre": "journal-article", "is_paratext": false, "published_date": "2020-08-01", "year": 2020, "journal_name": "The Journal of Prosthetic Dentistry", "journal_issns": "0022-3913", "journal_issn_l": "0022-3913", "journal_is_oa": false, "journal_is_in_doaj": false, "publisher": "Elsevier BV", "is_oa": true, "oa_status": "hybrid", "has_repository_copy": true, "best_oa_location": {"updated": "2022-04-18T23:27:37.134079", "url": "http://www.thejpd.org/article/S0022391319304895/pdf", "url_for_pdf": "http://www.thejpd.org/article/S0022391319304895/pdf", "url_for_landing_page": "https://doi.org/10.1016/j.prosdent.2019.07.013", "evidence": "open (via crossref license)", "license": "cc-by-nc-nd", "version": "publishedVersion", "host_type": "publisher", "is_best": true, "pmh_id": null, "endpoint_id": null, "repository_institution": null, "oa_date": "2019-09-04"}, "first_oa_location": {"updated": "2022-04-18T23:27:37.134079", "url": "http://www.thejpd.org/article/S0022391319304895/pdf", "url_for_pdf": "http://www.thejpd.org/article/S0022391319304895/pdf", "url_for_landing_page": "https://doi.org/10.1016/j.prosdent.2019.07.013", "evidence": "open (via crossref license)", "license": "cc-by-nc-nd", "version": "publishedVersion", "host_type": "publisher", "is_best": true, "pmh_id": null, "endpoint_id": null, "repository_institution": null, "oa_date": "2019-09-04"}, "oa_locations": [{"updated": "2022-04-18T23:27:37.134079", "url": "http://www.thejpd.org/article/S0022391319304895/pdf", "url_for_pdf": "http://www.thejpd.org/article/S0022391319304895/pdf", "url_for_landing_page": "https://doi.org/10.1016/j.prosdent.2019.07.013", "evidence": "open (via crossref license)", "license": "cc-by-nc-nd", "version": "publishedVersion", "host_type": "publisher", "is_best": true, "pmh_id": null, "endpoint_id": null, "repository_institution": null, "oa_date": "2019-09-04"}, {"updated": "2021-12-15T19:14:32.679671", "url": "https://boris.unibe.ch/136240/1/Qin%20Yue%20et%20al_JPD%202019.pdf", "url_for_pdf": "https://boris.unibe.ch/136240/1/Qin%20Yue%20et%20al_JPD%202019.pdf", "url_for_landing_page": "https://boris.unibe.ch/136240/1/Qin%20Yue%20et%20al_JPD%202019.pdf", "evidence": "oa repository (via OAI-PMH doi match)", "license": null, "version": "publishedVersion", "host_type": "repository", "is_best": false, "pmh_id": "oai:boris.unibe.ch:136240", "endpoint_id": "bd26192e3f21d590a4f", "repository_institution": "University Library Bern - BORIS - Bern Open Repository and Information System", "oa_date": null}, {"updated": "2022-03-19T07:23:42.977672", "url": "https://archive-ouverte.unige.ch/unige:143522/ATTACHMENT01", "url_for_pdf": "https://archive-ouverte.unige.ch/unige:143522/ATTACHMENT01", "url_for_landing_page": "https://archive-ouverte.unige.ch/unige:143522", "evidence": "oa repository (via OAI-PMH doi match)", "license": "cc-by-nc-nd", "version": "publishedVersion", "host_type": "repository", "is_best": false, "pmh_id": "oai:unige.ch:unige:143522", "endpoint_id": "10e4b9f6451f62e44e8", "repository_institution": "University of Geneva - Archive ouverte UNIGE", "oa_date": "2020-10-27"}], "oa_locations_embargoed": [], "updated": "2021-09-18T04:12:25.644945", "data_standard": 2, "z_authors": [{"given": "Qin", "family": "Yue", "sequence": "first"}, {"ORCID": "http://orcid.org/0000-0002-7101-363X", "given": "Burak", "family": "Yilmaz", "sequence": "additional", "authenticated-orcid": false}, {"ORCID": "http://orcid.org/0000-0003-1047-5571", "given": "Samir", "family": "Abou-Ayash", "sequence": "additional", "authenticated-orcid": false}, {"given": "Patrick", "family": "Zimmermann", "sequence": "additional"}, {"given": "Urs", "family": "Br\u00e4gger", "sequence": "additional"}, {"ORCID": "http://orcid.org/0000-0001-9700-5534", "given": "Martin", "family": "Schimmel", "sequence": "additional", "authenticated-orcid": false}]}