{"doi": "10.1007/s00784-013-0978-3", "doi_url": "https://doi.org/10.1007/s00784-013-0978-3", "title": "Adhesive restoration of anterior endodontically treated teeth: influence of post length on fracture strength", "genre": "journal-article", "is_paratext": false, "published_date": "2013-04-20", "year": 2013, "journal_name": "Clinical Oral Investigations", "journal_issns": "1432-6981,1436-3771", "journal_issn_l": "1432-6981", "journal_is_oa": false, "journal_is_in_doaj": false, "publisher": "Springer Science and Business Media LLC", "is_oa": true, "oa_status": "green", "has_repository_copy": true, "best_oa_location": {"updated": "2022-03-23T02:23:29.515512", "url": "https://archive-ouverte.unige.ch/unige:38590/ATTACHMENT01", "url_for_pdf": "https://archive-ouverte.unige.ch/unige:38590/ATTACHMENT01", "url_for_landing_page": "https://archive-ouverte.unige.ch/unige:38590", "evidence": "oa repository (via OAI-PMH doi match)", "license": null, "version": "publishedVersion", "host_type": "repository", "is_best": true, "pmh_id": "oai:unige.ch:unige:38590", "endpoint_id": "10e4b9f6451f62e44e8", "repository_institution": "University of Geneva - Archive ouverte UNIGE", "oa_date": "2020-12-24"}, "first_oa_location": {"updated": "2022-03-23T02:23:29.515512", "url": "https://archive-ouverte.unige.ch/unige:38590/ATTACHMENT01", "url_for_pdf": "https://archive-ouverte.unige.ch/unige:38590/ATTACHMENT01", "url_for_landing_page": "https://archive-ouverte.unige.ch/unige:38590", "evidence": "oa repository (via OAI-PMH doi match)", "license": null, "version": "publishedVersion", "host_type": "repository", "is_best": true, "pmh_id": "oai:unige.ch:unige:38590", "endpoint_id": "10e4b9f6451f62e44e8", "repository_institution": "University of Geneva - Archive ouverte UNIGE", "oa_date": "2020-12-24"}, "oa_locations": [{"updated": "2022-03-23T02:23:29.515512", "url": "https://archive-ouverte.unige.ch/unige:38590/ATTACHMENT01", "url_for_pdf": "https://archive-ouverte.unige.ch/unige:38590/ATTACHMENT01", "url_for_landing_page": "https://archive-ouverte.unige.ch/unige:38590", "evidence": "oa repository (via OAI-PMH doi match)", "license": null, "version": "publishedVersion", "host_type": "repository", "is_best": true, "pmh_id": "oai:unige.ch:unige:38590", "endpoint_id": "10e4b9f6451f62e44e8", "repository_institution": "University of Geneva - Archive ouverte UNIGE", "oa_date": "2020-12-24"}], "oa_locations_embargoed": [], "updated": "2021-01-19T20:27:43.732719", "data_standard": 2, "z_authors": [{"given": "Ana\u00efs", "family": "Ram\u00edrez-Sebasti\u00e0", "sequence": "first"}, {"given": "Tissiana", "family": "Bortolotto", "sequence": "additional"}, {"given": "Maria", "family": "Cattani-Lorente", "sequence": "additional"}, {"given": "Lluis", "family": "Giner", "sequence": "additional"}, {"given": "Miguel", "family": "Roig", "sequence": "additional"}, {"given": "Ivo", "family": "Krejci", "sequence": "additional"}]}