{"doi": "10.1016/j.ajic.2010.09.007", "doi_url": "https://doi.org/10.1016/j.ajic.2010.09.007", "title": "Hand hygiene practices and adherence determinants in surgical wards across Europe and Israel: A multicenter observational study", "genre": "journal-article", "is_paratext": false, "published_date": "2011-08-01", "year": 2011, "journal_name": "American Journal of Infection Control", "journal_issns": "0196-6553", "journal_issn_l": "0196-6553", "journal_is_oa": false, "journal_is_in_doaj": false, "publisher": "Elsevier BV", "is_oa": false, "oa_status": "closed", "has_repository_copy": false, "best_oa_location": null, "first_oa_location": null, "oa_locations": [], "oa_locations_embargoed": [], "updated": "2021-01-16T01:38:56.352344", "data_standard": 2, "z_authors": [{"given": "Andie", "family": "Lee", "sequence": "first"}, {"given": "Annie", "family": "Chalfine", "sequence": "additional"}, {"given": "George L.", "family": "Daikos", "sequence": "additional"}, {"given": "Silvia", "family": "Garilli", "sequence": "additional"}, {"given": "Biljana", "family": "Jovanovic", "sequence": "additional"}, {"given": "Sebastian", "family": "Lemmen", "sequence": "additional"}, {"given": "Jos\u00e9 Antonio", "family": "Mart\u00ednez", "sequence": "additional"}, {"given": "Cristina", "family": "Masuet Aumatell", "sequence": "additional"}, {"given": "Joanne", "family": "McEwen", "sequence": "additional"}, {"given": "Didier", "family": "Pittet", "sequence": "additional"}, {"given": "Bina", "family": "Rubinovitch", "sequence": "additional"}, {"given": "Hugo", "family": "Sax", "sequence": "additional"}, {"given": "Stephan", "family": "Harbarth", "sequence": "additional"}]}