{"doi": "10.3389/fendo.2017.00384", "doi_url": "https://doi.org/10.3389/fendo.2017.00384", "title": "Oncocytic Adrenocortical Neoplasm with Concomitant Papillary Thyroid Cancer", "genre": "journal-article", "is_paratext": false, "published_date": "2018-01-22", "year": 2018, "journal_name": "Frontiers in Endocrinology", "journal_issns": "1664-2392", "journal_issn_l": "1664-2392", "journal_is_oa": true, "journal_is_in_doaj": true, "publisher": "Frontiers Media SA", "is_oa": true, "oa_status": "gold", "has_repository_copy": true, "best_oa_location": {"updated": "2022-04-19T01:52:48.250333", "url": "https://www.frontiersin.org/articles/10.3389/fendo.2017.00384/pdf", "url_for_pdf": "https://www.frontiersin.org/articles/10.3389/fendo.2017.00384/pdf", "url_for_landing_page": "https://doi.org/10.3389/fendo.2017.00384", "evidence": "oa journal (via doaj)", "license": "cc-by", "version": "publishedVersion", "host_type": "publisher", "is_best": true, "pmh_id": null, "endpoint_id": null, "repository_institution": null, "oa_date": "2018-01-22"}, "first_oa_location": {"updated": "2022-04-19T01:52:48.250333", "url": "https://www.frontiersin.org/articles/10.3389/fendo.2017.00384/pdf", "url_for_pdf": "https://www.frontiersin.org/articles/10.3389/fendo.2017.00384/pdf", "url_for_landing_page": "https://doi.org/10.3389/fendo.2017.00384", "evidence": "oa journal (via doaj)", "license": "cc-by", "version": "publishedVersion", "host_type": "publisher", "is_best": true, "pmh_id": null, "endpoint_id": null, "repository_institution": null, "oa_date": "2018-01-22"}, "oa_locations": [{"updated": "2022-04-19T01:52:48.250333", "url": "https://www.frontiersin.org/articles/10.3389/fendo.2017.00384/pdf", "url_for_pdf": "https://www.frontiersin.org/articles/10.3389/fendo.2017.00384/pdf", "url_for_landing_page": "https://doi.org/10.3389/fendo.2017.00384", "evidence": "oa journal (via doaj)", "license": "cc-by", "version": "publishedVersion", "host_type": "publisher", "is_best": true, "pmh_id": null, "endpoint_id": null, "repository_institution": null, "oa_date": "2018-01-22"}, {"updated": null, "url": "https://europepmc.org/articles/pmc5786566?pdf=render", "url_for_pdf": "https://europepmc.org/articles/pmc5786566?pdf=render", "url_for_landing_page": "https://europepmc.org/articles/pmc5786566", "evidence": "oa repository (via OAI-PMH doi match)", "license": "cc-by", "version": "publishedVersion", "host_type": "repository", "is_best": false, "pmh_id": "oai:europepmc.org:oyPRBnmiqkzB7n7cZDa7", "endpoint_id": "b5e840539009389b1a6", "repository_institution": "PubMed Central - Europe PMC", "oa_date": null}, {"updated": "2022-03-10T20:20:31.972495", "url": "https://archive-ouverte.unige.ch/unige:103524/ATTACHMENT01", "url_for_pdf": "https://archive-ouverte.unige.ch/unige:103524/ATTACHMENT01", "url_for_landing_page": "https://archive-ouverte.unige.ch/unige:103524", "evidence": "oa repository (via OAI-PMH doi match)", "license": "cc-by", "version": "publishedVersion", "host_type": "repository", "is_best": false, "pmh_id": "oai:unige.ch:unige:103524", "endpoint_id": "10e4b9f6451f62e44e8", "repository_institution": "University of Geneva - Archive ouverte UNIGE", "oa_date": null}, {"updated": "2022-04-19T01:52:48.250430", "url": "https://www.ncbi.nlm.nih.gov/pmc/articles/PMC5786566", "url_for_pdf": null, "url_for_landing_page": "https://www.ncbi.nlm.nih.gov/pmc/articles/PMC5786566", "evidence": "oa repository (via pmcid lookup)", "license": null, "version": "publishedVersion", "host_type": "repository", "is_best": false, "pmh_id": null, "endpoint_id": null, "repository_institution": null, "oa_date": null}], "oa_locations_embargoed": [], "updated": "2022-03-26T16:45:43.421832", "data_standard": 2, "z_authors": [{"given": "Michele", "family": "Podetta", "sequence": "first"}, {"given": "Marc", "family": "Pusztaszeri", "sequence": "additional"}, {"given": "Christian", "family": "Toso", "sequence": "additional"}, {"given": "Michel", "family": "Procopiou", "sequence": "additional"}, {"given": "Fr\u00e9d\u00e9ric", "family": "Triponez", "sequence": "additional"}, {"given": "Samira Mercedes", "family": "Sadowski", "sequence": "additional"}]}