{"doi": "10.1002/mrm.24931", "doi_url": "https://doi.org/10.1002/mrm.24931", "title": "An improved trap design for decoupling multinuclear RF coils", "genre": "journal-article", "is_paratext": false, "published_date": "2013-09-04", "year": 2013, "journal_name": "Magnetic Resonance in Medicine", "journal_issns": "0740-3194,1522-2594", "journal_issn_l": "0740-3194", "journal_is_oa": false, "journal_is_in_doaj": false, "publisher": "Wiley", "is_oa": true, "oa_status": "bronze", "has_repository_copy": true, "best_oa_location": {"updated": "2018-09-13T20:26:23.221183", "url": "https://onlinelibrary.wiley.com/doi/pdfdirect/10.1002/mrm.24931", "url_for_pdf": "https://onlinelibrary.wiley.com/doi/pdfdirect/10.1002/mrm.24931", "url_for_landing_page": "https://doi.org/10.1002/mrm.24931", "evidence": "open (via free pdf)", "license": null, "version": "publishedVersion", "host_type": "publisher", "is_best": true, "pmh_id": null, "endpoint_id": null, "repository_institution": null, "oa_date": null}, "first_oa_location": {"updated": "2022-03-22T12:08:07.819424", "url": "https://archive-ouverte.unige.ch/unige:45000/ATTACHMENT01", "url_for_pdf": "https://archive-ouverte.unige.ch/unige:45000/ATTACHMENT01", "url_for_landing_page": "https://archive-ouverte.unige.ch/unige:45000", "evidence": "oa repository (via OAI-PMH doi match)", "license": null, "version": "publishedVersion", "host_type": "repository", "is_best": false, "pmh_id": "oai:unige.ch:unige:45000", "endpoint_id": "10e4b9f6451f62e44e8", "repository_institution": "University of Geneva - Archive ouverte UNIGE", "oa_date": "2020-12-24"}, "oa_locations": [{"updated": "2018-09-13T20:26:23.221183", "url": "https://onlinelibrary.wiley.com/doi/pdfdirect/10.1002/mrm.24931", "url_for_pdf": "https://onlinelibrary.wiley.com/doi/pdfdirect/10.1002/mrm.24931", "url_for_landing_page": "https://doi.org/10.1002/mrm.24931", "evidence": "open (via free pdf)", "license": null, "version": "publishedVersion", "host_type": "publisher", "is_best": true, "pmh_id": null, "endpoint_id": null, "repository_institution": null, "oa_date": null}, {"updated": "2022-03-22T12:08:07.819424", "url": "https://archive-ouverte.unige.ch/unige:45000/ATTACHMENT01", "url_for_pdf": "https://archive-ouverte.unige.ch/unige:45000/ATTACHMENT01", "url_for_landing_page": "https://archive-ouverte.unige.ch/unige:45000", "evidence": "oa repository (via OAI-PMH doi match)", "license": null, "version": "publishedVersion", "host_type": "repository", "is_best": false, "pmh_id": "oai:unige.ch:unige:45000", "endpoint_id": "10e4b9f6451f62e44e8", "repository_institution": "University of Geneva - Archive ouverte UNIGE", "oa_date": "2020-12-24"}, {"updated": "2022-03-21T02:46:56.445023", "url": "https://infoscience.epfl.ch/record/188385/files/Meyerspeer_Traps_2014.pdf", "url_for_pdf": "https://infoscience.epfl.ch/record/188385/files/Meyerspeer_Traps_2014.pdf", "url_for_landing_page": "https://infoscience.epfl.ch/record/188385/files/Meyerspeer_Traps_2014.pdf", "evidence": "oa repository (via OAI-PMH doi match)", "license": null, "version": "submittedVersion", "host_type": "repository", "is_best": false, "pmh_id": "oai:infoscience.tind.io:188385", "endpoint_id": "7760ae59248d04d82fd", "repository_institution": "Ecole Polytechnique F\u00e9d\u00e9rale de Lausanne - Infoscience", "oa_date": null}], "oa_locations_embargoed": [], "updated": "2022-03-22T14:28:59.463079", "data_standard": 2, "z_authors": [{"given": "Martin", "family": "Meyerspeer", "sequence": "first", "affiliation": [{"name": "LIFMET\u00c9cole Polytechnique F\u00e9d\u00e9rale de LausanneLausanne Switzerland"}, {"name": "Center for Medical Physics and Biomedical EngineeringMedical University of Vienna Austria"}, {"name": "MR Centre of ExcellenceMedical University of Vienna Austria"}]}, {"given": "Eulalia Ser\u00e9s", "family": "Roig", "sequence": "additional", "affiliation": [{"name": "LIFMET\u00c9cole Polytechnique F\u00e9d\u00e9rale de LausanneLausanne Switzerland"}, {"name": "Department of RadiologyUniversity of Lausanne Lausanne Switzerland"}]}, {"given": "Rolf", "family": "Gruetter", "sequence": "additional", "affiliation": [{"name": "LIFMET\u00c9cole Polytechnique F\u00e9d\u00e9rale de LausanneLausanne Switzerland"}, {"name": "Department of RadiologyUniversity of Lausanne Lausanne Switzerland"}, {"name": "Department of RadiologyUniversity of GenevaGeneva Switzerland."}]}, {"given": "Arthur W.", "family": "Magill", "sequence": "additional", "affiliation": [{"name": "LIFMET\u00c9cole Polytechnique F\u00e9d\u00e9rale de LausanneLausanne Switzerland"}, {"name": "Department of RadiologyUniversity of Lausanne Lausanne Switzerland"}]}]}