{"doi": "10.1016/j.healun.2020.03.022", "doi_url": "https://doi.org/10.1016/j.healun.2020.03.022", "title": "Lung transplantation as standard of care for advanced cystic fibrosis lung disease", "genre": "journal-article", "is_paratext": false, "published_date": "2020-06-01", "year": 2020, "journal_name": "The Journal of Heart and Lung Transplantation", "journal_issns": "1053-2498", "journal_issn_l": "1053-2498", "journal_is_oa": false, "journal_is_in_doaj": false, "publisher": "Elsevier BV", "is_oa": true, "oa_status": "bronze", "has_repository_copy": false, "best_oa_location": {"updated": "2021-02-21T09:45:52.975441", "url": "https://www.jhltonline.org/article/S1053-2498(20)31483-2/pdf", "url_for_pdf": "https://www.jhltonline.org/article/S1053-2498(20)31483-2/pdf", "url_for_landing_page": "https://doi.org/10.1016/j.healun.2020.03.022", "evidence": "open (via free pdf)", "license": null, "version": "publishedVersion", "host_type": "publisher", "is_best": true, "pmh_id": null, "endpoint_id": null, "repository_institution": null, "oa_date": null}, "first_oa_location": {"updated": "2021-02-21T09:45:52.975441", "url": "https://www.jhltonline.org/article/S1053-2498(20)31483-2/pdf", "url_for_pdf": "https://www.jhltonline.org/article/S1053-2498(20)31483-2/pdf", "url_for_landing_page": "https://doi.org/10.1016/j.healun.2020.03.022", "evidence": "open (via free pdf)", "license": null, "version": "publishedVersion", "host_type": "publisher", "is_best": true, "pmh_id": null, "endpoint_id": null, "repository_institution": null, "oa_date": null}, "oa_locations": [{"updated": "2021-02-21T09:45:52.975441", "url": "https://www.jhltonline.org/article/S1053-2498(20)31483-2/pdf", "url_for_pdf": "https://www.jhltonline.org/article/S1053-2498(20)31483-2/pdf", "url_for_landing_page": "https://doi.org/10.1016/j.healun.2020.03.022", "evidence": "open (via free pdf)", "license": null, "version": "publishedVersion", "host_type": "publisher", "is_best": true, "pmh_id": null, "endpoint_id": null, "repository_institution": null, "oa_date": null}], "oa_locations_embargoed": [], "updated": "2021-02-21T09:48:34.731873", "data_standard": 2, "z_authors": [{"given": "Christian", "family": "Benden", "sequence": "first"}]}