{"doi": "10.1016/j.prosdent.2017.11.005", "doi_url": "https://doi.org/10.1016/j.prosdent.2017.11.005", "title": "A safe holder for adjusting indirect prostheses: The silicone cube technique", "genre": "journal-article", "is_paratext": false, "published_date": "2018-08-01", "year": 2018, "journal_name": "The Journal of Prosthetic Dentistry", "journal_issns": "0022-3913", "journal_issn_l": "0022-3913", "journal_is_oa": false, "journal_is_in_doaj": false, "publisher": "Elsevier BV", "is_oa": true, "oa_status": "bronze", "has_repository_copy": false, "best_oa_location": {"updated": "2021-02-23T12:04:26.660382", "url": "https://www.thejpd.org/article/S0022-3913(17)30736-9/pdf", "url_for_pdf": "https://www.thejpd.org/article/S0022-3913(17)30736-9/pdf", "url_for_landing_page": "https://doi.org/10.1016/j.prosdent.2017.11.005", "evidence": "open (via free pdf)", "license": null, "version": "publishedVersion", "host_type": "publisher", "is_best": true, "pmh_id": null, "endpoint_id": null, "repository_institution": null, "oa_date": null}, "first_oa_location": {"updated": "2021-02-23T12:04:26.660382", "url": "https://www.thejpd.org/article/S0022-3913(17)30736-9/pdf", "url_for_pdf": "https://www.thejpd.org/article/S0022-3913(17)30736-9/pdf", "url_for_landing_page": "https://doi.org/10.1016/j.prosdent.2017.11.005", "evidence": "open (via free pdf)", "license": null, "version": "publishedVersion", "host_type": "publisher", "is_best": true, "pmh_id": null, "endpoint_id": null, "repository_institution": null, "oa_date": null}, "oa_locations": [{"updated": "2021-02-23T12:04:26.660382", "url": "https://www.thejpd.org/article/S0022-3913(17)30736-9/pdf", "url_for_pdf": "https://www.thejpd.org/article/S0022-3913(17)30736-9/pdf", "url_for_landing_page": "https://doi.org/10.1016/j.prosdent.2017.11.005", "evidence": "open (via free pdf)", "license": null, "version": "publishedVersion", "host_type": "publisher", "is_best": true, "pmh_id": null, "endpoint_id": null, "repository_institution": null, "oa_date": null}], "oa_locations_embargoed": [], "updated": "2021-02-23T12:07:10.569641", "data_standard": 2, "z_authors": [{"given": "Kelvin I.", "family": "Afrashtehfar", "sequence": "first"}, {"given": "Daniel", "family": "Buser", "sequence": "additional"}, {"given": "Urs C.", "family": "Belser", "sequence": "additional"}]}