{"doi": "10.1111/j.1532-5415.2012.04179.x", "doi_url": "https://doi.org/10.1111/j.1532-5415.2012.04179.x", "title": "Mycobacterial Arthritis", "genre": "journal-article", "is_paratext": false, "published_date": "2012-10-01", "year": 2012, "journal_name": "Journal of the American Geriatrics Society", "journal_issns": "0002-8614", "journal_issn_l": "0002-8614", "journal_is_oa": false, "journal_is_in_doaj": false, "publisher": "Wiley", "is_oa": false, "oa_status": "closed", "has_repository_copy": false, "best_oa_location": null, "first_oa_location": null, "oa_locations": [], "oa_locations_embargoed": [], "updated": "2021-01-17T01:56:30.112954", "data_standard": 2, "z_authors": [{"given": "Alexandre", "family": "Forster", "sequence": "first", "affiliation": [{"name": "Department of Internal Medicine; Rehabilitation and Geriatrics; Geneva University Hospitals; Geneva; Switzerland"}]}, {"given": "No\u00e9mie", "family": "Assir", "sequence": "additional", "affiliation": [{"name": "Department of Internal Medicine; Rehabilitation and Geriatrics; Geneva University Hospitals; Geneva; Switzerland"}]}, {"given": "Grigorios", "family": "Notaridis", "sequence": "additional", "affiliation": [{"name": "Department of Internal Medicine; Rehabilitation and Geriatrics; Geneva University Hospitals; Geneva; Switzerland"}]}, {"given": "Dimitrios", "family": "Samaras", "sequence": "additional", "affiliation": [{"name": "Department of Medical Specialties and Clinical Nutrition; Geneva University Hospitals; Geneva; Switzerland"}]}, {"given": "Nikolaos", "family": "Samaras", "sequence": "additional", "affiliation": [{"name": "Department of Internal Medicine; Rehabilitation and Geriatrics; Geneva University Hospitals; Geneva; Switzerland"}]}]}