{"doi": "10.1016/j.mric.2011.08.013", "doi_url": "https://doi.org/10.1016/j.mric.2011.08.013", "title": "MR Imaging of Neonatal Brain Infections", "genre": "journal-article", "is_paratext": false, "published_date": "2011-11-01", "year": 2011, "journal_name": "Magnetic Resonance Imaging Clinics of North America", "journal_issns": "1064-9689", "journal_issn_l": "1064-9689", "journal_is_oa": false, "journal_is_in_doaj": false, "publisher": "Elsevier BV", "is_oa": false, "oa_status": "closed", "has_repository_copy": false, "best_oa_location": null, "first_oa_location": null, "oa_locations": [], "oa_locations_embargoed": [], "updated": "2021-01-16T01:54:30.265686", "data_standard": 2, "z_authors": [{"given": "Jacques F.", "family": "Schneider", "sequence": "first"}, {"given": "Sylviane", "family": "Hanquinet", "sequence": "additional"}, {"given": "Mariasavina", "family": "Severino", "sequence": "additional"}, {"given": "Andrea", "family": "Rossi", "sequence": "additional"}]}