{"doi": "10.1111/codi.12593", "doi_url": "https://doi.org/10.1111/codi.12593", "title": "Near infra-red laparoscopic assessment of the adequacy of blood perfusion of intestinal anastomosis - a video vignette", "genre": "journal-article", "is_paratext": false, "published_date": "2014-07-17", "year": 2014, "journal_name": "Colorectal Disease", "journal_issns": "1462-8910", "journal_issn_l": "1462-8910", "journal_is_oa": false, "journal_is_in_doaj": false, "publisher": "Wiley", "is_oa": false, "oa_status": "closed", "has_repository_copy": false, "best_oa_location": null, "first_oa_location": null, "oa_locations": [], "oa_locations_embargoed": [], "updated": "2021-01-19T10:48:42.664631", "data_standard": 2, "z_authors": [{"given": "F.", "family": "Ris", "sequence": "first", "affiliation": [{"name": "Department of Colorectal Surgery; Geneva University Hospital; Geneva Switzerland"}]}, {"given": "R.", "family": "Hompes", "sequence": "additional", "affiliation": [{"name": "Department of Colorectal Surgery; Oxford Radcliffe Hospitals; Oxford UK"}]}, {"given": "I.", "family": "Lindsey", "sequence": "additional", "affiliation": [{"name": "Department of Colorectal Surgery; Oxford Radcliffe Hospitals; Oxford UK"}]}, {"given": "C.", "family": "Cunningham", "sequence": "additional", "affiliation": [{"name": "Department of Colorectal Surgery; Oxford Radcliffe Hospitals; Oxford UK"}]}, {"given": "N. J.", "family": "Mortensen", "sequence": "additional", "affiliation": [{"name": "Department of Colorectal Surgery; Oxford Radcliffe Hospitals; Oxford UK"}]}, {"given": "R. A.", "family": "Cahill", "sequence": "additional", "affiliation": [{"name": "Department of Colorectal Surgery; Oxford Radcliffe Hospitals; Oxford UK"}]}]}