{"doi": "10.3851/imp2103", "doi_url": "https://doi.org/10.3851/imp2103", "title": "Responses of solid organ transplant recipients to the AS03-adjuvanted pandemic influenza vaccine", "genre": "journal-article", "is_paratext": false, "published_date": "2012-01-01", "year": 2012, "journal_name": "Antiviral Therapy", "journal_issns": "1359-6535", "journal_issn_l": "1359-6535", "journal_is_oa": false, "journal_is_in_doaj": false, "publisher": "SAGE Publications", "is_oa": false, "oa_status": "closed", "has_repository_copy": false, "best_oa_location": null, "first_oa_location": null, "oa_locations": [], "oa_locations_embargoed": [], "updated": "2021-08-28T11:42:43.292256", "data_standard": 2, "z_authors": [{"given": "Claire-Anne", "family": "Siegrist", "sequence": "first"}, {"name": "the H1N1 study group", "sequence": "first"}, {"given": "Juan", "family": "Ambrosioni", "sequence": "additional"}, {"given": "Michael", "family": "Bel", "sequence": "additional"}, {"given": "Christophe", "family": "Combescure", "sequence": "additional"}, {"given": "Karine", "family": "Hadaya", "sequence": "additional"}, {"given": "Pierre-Yves", "family": "Martin", "sequence": "additional"}, {"given": "Paola M", "family": "Soccal", "sequence": "additional"}, {"given": "Thierry", "family": "Berney", "sequence": "additional"}, {"given": "Stephane", "family": "Noble", "sequence": "additional"}, {"given": "Sara", "family": "Meier", "sequence": "additional"}, {"given": "Klara", "family": "Posfay-Barbe", "sequence": "additional"}, {"given": "Stephane", "family": "Grillet", "sequence": "additional"}, {"given": "Laurent", "family": "Kaiser", "sequence": "additional"}, {"given": "Christian", "family": "van Delden", "sequence": "additional"}]}