{"doi": "10.1159/000484566", "doi_url": "https://doi.org/10.1159/000484566", "title": "Sugar-Sweetened Beverages and Weight Gain in Children and Adults: A Systematic Review from 2013 to 2015 and a Comparison with Previous Studies", "genre": "journal-article", "is_paratext": false, "published_date": "2017-01-01", "year": 2017, "journal_name": "Obesity Facts", "journal_issns": "1662-4025,1662-4033", "journal_issn_l": "1662-4025", "journal_is_oa": true, "journal_is_in_doaj": true, "publisher": "S. Karger AG", "is_oa": true, "oa_status": "gold", "has_repository_copy": true, "best_oa_location": {"updated": "2022-04-19T00:38:33.354009", "url": "https://www.karger.com/Article/Pdf/484566", "url_for_pdf": "https://www.karger.com/Article/Pdf/484566", "url_for_landing_page": "https://doi.org/10.1159/000484566", "evidence": "oa journal (via doaj)", "license": "cc-by-nc-nd", "version": "publishedVersion", "host_type": "publisher", "is_best": true, "pmh_id": null, "endpoint_id": null, "repository_institution": null, "oa_date": "2017-01-01"}, "first_oa_location": {"updated": "2022-04-19T00:38:33.354009", "url": "https://www.karger.com/Article/Pdf/484566", "url_for_pdf": "https://www.karger.com/Article/Pdf/484566", "url_for_landing_page": "https://doi.org/10.1159/000484566", "evidence": "oa journal (via doaj)", "license": "cc-by-nc-nd", "version": "publishedVersion", "host_type": "publisher", "is_best": true, "pmh_id": null, "endpoint_id": null, "repository_institution": null, "oa_date": "2017-01-01"}, "oa_locations": [{"updated": "2022-04-19T00:38:33.354009", "url": "https://www.karger.com/Article/Pdf/484566", "url_for_pdf": "https://www.karger.com/Article/Pdf/484566", "url_for_landing_page": "https://doi.org/10.1159/000484566", "evidence": "oa journal (via doaj)", "license": "cc-by-nc-nd", "version": "publishedVersion", "host_type": "publisher", "is_best": true, "pmh_id": null, "endpoint_id": null, "repository_institution": null, "oa_date": "2017-01-01"}, {"updated": "2022-03-16T18:08:16.539261", "url": "https://europepmc.org/articles/pmc5836186?pdf=render", "url_for_pdf": "https://europepmc.org/articles/pmc5836186?pdf=render", "url_for_landing_page": "https://europepmc.org/articles/pmc5836186", "evidence": "oa repository (via OAI-PMH doi match)", "license": null, "version": "publishedVersion", "host_type": "repository", "is_best": false, "pmh_id": "oai:europepmc.org:FgrprbPPXjfMxPeE2xxX", "endpoint_id": "b5e840539009389b1a6", "repository_institution": "PubMed Central - Europe PMC", "oa_date": null}, {"updated": "2022-04-15T12:50:23.252502", "url": "https://dadun.unav.edu/bitstream/10171/53605/1/pdf.pdf", "url_for_pdf": "https://dadun.unav.edu/bitstream/10171/53605/1/pdf.pdf", "url_for_landing_page": "http://hdl.handle.net/10171/53605", "evidence": "oa repository (via OAI-PMH title and first author match)", "license": "cc-by-nc-nd", "version": "publishedVersion", "host_type": "repository", "is_best": false, "pmh_id": "oai:dadun.unav.edu:10171/53605", "endpoint_id": "952d9b6929670acaa49", "repository_institution": "University of Navarra - Deposito Adademico Digital Universidad De Navarra", "oa_date": null}, {"updated": "2022-01-24T02:17:02.940229", "url": "https://archive-ouverte.unige.ch/unige:108345/ATTACHMENT01", "url_for_pdf": "https://archive-ouverte.unige.ch/unige:108345/ATTACHMENT01", "url_for_landing_page": "https://archive-ouverte.unige.ch/unige:108345", "evidence": "oa repository (via OAI-PMH doi match)", "license": "cc-by-nc", "version": "publishedVersion", "host_type": "repository", "is_best": false, "pmh_id": "oai:unige.ch:unige:108345", "endpoint_id": "10e4b9f6451f62e44e8", "repository_institution": "University of Geneva - Archive ouverte UNIGE", "oa_date": null}, {"updated": "2022-04-19T00:38:33.354164", "url": "https://www.ncbi.nlm.nih.gov/pmc/articles/PMC5836186", "url_for_pdf": null, "url_for_landing_page": "https://www.ncbi.nlm.nih.gov/pmc/articles/PMC5836186", "evidence": "oa repository (via pmcid lookup)", "license": null, "version": "publishedVersion", "host_type": "repository", "is_best": false, "pmh_id": null, "endpoint_id": null, "repository_institution": null, "oa_date": null}], "oa_locations_embargoed": [], "updated": "2022-04-18T01:37:18.041042", "data_standard": 2, "z_authors": [{"ORCID": "http://orcid.org/0000-0002-1991-6700", "given": "Maria", "family": "Luger", "sequence": "first", "authenticated-orcid": false}, {"given": "Max", "family": "Lafontan", "sequence": "additional"}, {"given": "Maira", "family": "Bes-Rastrollo", "sequence": "additional"}, {"given": "Eva", "family": "Winzer", "sequence": "additional"}, {"given": "Volkan", "family": "Yumuk", "sequence": "additional"}, {"given": "Nathalie", "family": "Farpour-Lambert", "sequence": "additional"}]}