{"doi": "10.1016/j.accpm.2018.10.004", "doi_url": "https://doi.org/10.1016/j.accpm.2018.10.004", "title": "Management of antiplatelet therapy for non elective invasive procedures of bleeding complications: proposals from the French working group on perioperative haemostasis (GIHP), in collaboration with the French Society of Anaesthesia and Intensive Care Medicine (SFAR)", "genre": "journal-article", "is_paratext": false, "published_date": "2019-06-01", "year": 2019, "journal_name": "Anaesthesia Critical Care & Pain Medicine", "journal_issns": "2352-5568", "journal_issn_l": "2352-5568", "journal_is_oa": false, "journal_is_in_doaj": false, "publisher": "Elsevier BV", "is_oa": true, "oa_status": "hybrid", "has_repository_copy": true, "best_oa_location": {"updated": "2022-04-19T02:07:26.338386", "url": "https://doi.org/10.1016/j.accpm.2018.10.004", "url_for_pdf": null, "url_for_landing_page": "https://doi.org/10.1016/j.accpm.2018.10.004", "evidence": "open (via crossref license)", "license": "cc-by", "version": "publishedVersion", "host_type": "publisher", "is_best": true, "pmh_id": null, "endpoint_id": null, "repository_institution": null, "oa_date": "2018-10-16"}, "first_oa_location": {"updated": "2022-04-19T02:07:26.338386", "url": "https://doi.org/10.1016/j.accpm.2018.10.004", "url_for_pdf": null, "url_for_landing_page": "https://doi.org/10.1016/j.accpm.2018.10.004", "evidence": "open (via crossref license)", "license": "cc-by", "version": "publishedVersion", "host_type": "publisher", "is_best": true, "pmh_id": null, "endpoint_id": null, "repository_institution": null, "oa_date": "2018-10-16"}, "oa_locations": [{"updated": "2022-04-19T02:07:26.338386", "url": "https://doi.org/10.1016/j.accpm.2018.10.004", "url_for_pdf": null, "url_for_landing_page": "https://doi.org/10.1016/j.accpm.2018.10.004", "evidence": "open (via crossref license)", "license": "cc-by", "version": "publishedVersion", "host_type": "publisher", "is_best": true, "pmh_id": null, "endpoint_id": null, "repository_institution": null, "oa_date": "2018-10-16"}, {"updated": "2021-04-16T23:02:35.857997", "url": "https://hal.sorbonne-universite.fr/hal-02935248/file/1-s2.0-S2352556818304156-main.pdf", "url_for_pdf": "https://hal.sorbonne-universite.fr/hal-02935248/file/1-s2.0-S2352556818304156-main.pdf", "url_for_landing_page": "https://hal.sorbonne-universite.fr/hal-02935248/file/1-s2.0-S2352556818304156-main.pdf", "evidence": "oa repository (via OAI-PMH doi match)", "license": "cc-by", "version": "publishedVersion", "host_type": "repository", "is_best": false, "pmh_id": "oai:HAL:hal-02935248v1", "endpoint_id": "b7862ef9ea7817152e1", "repository_institution": "Le Centre pour la Communication Scientifique Directe - HAL - Universit\u00e9 Paris Descartes", "oa_date": "2020-12-15"}, {"updated": "2021-04-16T23:03:46.927182", "url": "https://hal.sorbonne-universite.fr/hal-02935248/document", "url_for_pdf": "https://hal.sorbonne-universite.fr/hal-02935248/document", "url_for_landing_page": "https://hal.sorbonne-universite.fr/hal-02935248/document", "evidence": "oa repository (via OAI-PMH doi match)", "license": "cc-by", "version": "publishedVersion", "host_type": "repository", "is_best": false, "pmh_id": "oai:HAL:hal-02935248v1", "endpoint_id": "b7862ef9ea7817152e1", "repository_institution": "Le Centre pour la Communication Scientifique Directe - HAL - Universit\u00e9 Paris Descartes", "oa_date": "2020-12-15"}, {"updated": "2022-04-15T13:42:34.373849", "url": "https://lilloa.univ-lille.fr/bitstream/20.500.12210/34897/1/https%3a//hal.sorbonne-universite.fr/hal-02935248/document", "url_for_pdf": "https://lilloa.univ-lille.fr/bitstream/20.500.12210/34897/1/https%3a//hal.sorbonne-universite.fr/hal-02935248/document", "url_for_landing_page": "http://hdl.handle.net/20.500.12210/34897", "evidence": "oa repository (via OAI-PMH doi match)", "license": "cc-by", "version": "publishedVersion", "host_type": "repository", "is_best": false, "pmh_id": "oai:lilloa.univ-lille.fr:20.500.12210/34897", "endpoint_id": "mupipvwegdkufcuh27it", "repository_institution": "Universit\u00e9 de Lille (University Of Lille) - LillOA", "oa_date": "2021-01-05"}], "oa_locations_embargoed": [], "updated": "2022-04-14T20:28:04.988026", "data_standard": 2, "z_authors": [{"given": "A", "family": "Godier", "sequence": "first"}, {"given": "D", "family": "Garrigue", "sequence": "additional"}, {"ORCID": "http://orcid.org/0000-0001-6600-0263", "given": "D", "family": "Lasne", "sequence": "additional", "authenticated-orcid": false}, {"ORCID": "http://orcid.org/0000-0003-1546-0774", "given": "P", "family": "Fontana", "sequence": "additional", "authenticated-orcid": false}, {"given": "F", "family": "Bonhomme", "sequence": "additional"}, {"given": "JP", "family": "Collet", "sequence": "additional"}, {"given": "E", "family": "de Maistre", "sequence": "additional"}, {"given": "B", "family": "Ickx", "sequence": "additional"}, {"given": "Y", "family": "Gruel", "sequence": "additional"}, {"given": "M", "family": "Mazighi", "sequence": "additional"}, {"given": "P", "family": "Nguyen", "sequence": "additional"}, {"given": "A", "family": "Vincentelli", "sequence": "additional"}, {"given": "P", "family": "Albaladejo", "sequence": "additional"}, {"given": "T", "family": "Lecompte", "sequence": "additional"}]}