{"doi": "10.1016/s1665-2681(19)31848-4", "doi_url": "https://doi.org/10.1016/s1665-2681(19)31848-4", "title": "PTEN at the crossroad of metabolic diseases and cancer in the liver", "genre": "journal-article", "is_paratext": false, "published_date": "2008-07-01", "year": 2008, "journal_name": "Annals of Hepatology", "journal_issns": "1665-2681", "journal_issn_l": "1665-2681", "journal_is_oa": false, "journal_is_in_doaj": false, "publisher": "Elsevier BV", "is_oa": true, "oa_status": "hybrid", "has_repository_copy": false, "best_oa_location": {"updated": "2022-04-19T02:31:08.411439", "url": "https://doi.org/10.1016/s1665-2681(19)31848-4", "url_for_pdf": null, "url_for_landing_page": "https://doi.org/10.1016/s1665-2681(19)31848-4", "evidence": "open (via crossref license)", "license": "cc-by-nc-nd", "version": "publishedVersion", "host_type": "publisher", "is_best": true, "pmh_id": null, "endpoint_id": null, "repository_institution": null, "oa_date": "2019-06-25"}, "first_oa_location": {"updated": "2022-04-19T02:31:08.411439", "url": "https://doi.org/10.1016/s1665-2681(19)31848-4", "url_for_pdf": null, "url_for_landing_page": "https://doi.org/10.1016/s1665-2681(19)31848-4", "evidence": "open (via crossref license)", "license": "cc-by-nc-nd", "version": "publishedVersion", "host_type": "publisher", "is_best": true, "pmh_id": null, "endpoint_id": null, "repository_institution": null, "oa_date": "2019-06-25"}, "oa_locations": [{"updated": "2022-04-19T02:31:08.411439", "url": "https://doi.org/10.1016/s1665-2681(19)31848-4", "url_for_pdf": null, "url_for_landing_page": "https://doi.org/10.1016/s1665-2681(19)31848-4", "evidence": "open (via crossref license)", "license": "cc-by-nc-nd", "version": "publishedVersion", "host_type": "publisher", "is_best": true, "pmh_id": null, "endpoint_id": null, "repository_institution": null, "oa_date": "2019-06-25"}], "oa_locations_embargoed": [], "updated": "2021-01-15T23:20:09.623428", "data_standard": 2, "z_authors": [{"given": "Manlio", "family": "Vinciguerra", "sequence": "first"}, {"given": "Michelangelo", "family": "Foti", "sequence": "additional"}]}